imcsv/__init__.py
imcsv/exceptions.py
imcsv/imcsv.py
imcsv-0.0.1.dist-info/LICENSE
imcsv-0.0.1.dist-info/METADATA
imcsv-0.0.1.dist-info/WHEEL
imcsv-0.0.1.dist-info/top_level.txt
imcsv-0.0.1.dist-info/RECORD
