Metadata-Version: 2.1
Name: imcsv
Version: 0.0.1
Summary: In-Memory CSV file creator
Home-page: https://github.com/kaypee90/imcsv
Author: Kwabena Asante
License: MIT
Platform: UNKNOWN
Classifier: Programming Language :: Python :: 3
Classifier: License :: OSI Approved :: MIT License
Classifier: Operating System :: OS Independent
